{
  "version": 1,
  "author": "Labrez Shaikh",
  "editor": "wokwi",
  "parts": [
    {
      "type": "board-esp32-s3-devkitc-1",
      "id": "esp",
      "top": -0.18,
      "left": 14.17,
      "attrs": { "builder": "esp-idf" }
    },
    {
      "type": "board-ssd1306",
      "id": "oled1",
      "top": -217.66,
      "left": -76.57,
      "attrs": { "i2cAddress": "0x3c" }
    },
    {
      "type": "board-ssd1306",
      "id": "oled2",
      "top": 70.34,
      "left": -162.97,
      "attrs": { "i2cAddress": "0x3c" }
    },
    { "type": "wokwi-neopixel", "id": "rgb1", "top": -13.1, "left": -183.4, "attrs": {} },
    {
      "type": "wokwi-pushbutton",
      "id": "btn1",
      "top": -176.2,
      "left": -57.6,
      "attrs": { "color": "green", "xray": "1" }
    },
    {
      "type": "wokwi-pushbutton",
      "id": "btn2",
      "top": -22.6,
      "left": -86.4,
      "attrs": { "color": "green", "xray": "" }
    }
  ],
  "connections": [
    [ "esp:TX", "$serialMonitor:RX", "", [] ],
    [ "esp:RX", "$serialMonitor:TX", "", [] ],
    [ "oled2:GND", "esp:GND.1", "black", [ "v-19.2", "h-48", "v172.8" ] ],
    [ "esp:3V3.2", "oled2:VCC", "red", [ "h-134.45" ] ],
    [ "oled2:SCL", "esp:9", "green", [ "v-19.2", "h57.9", "v57.6", "h0", "v48", "h67.2" ] ],
    [ "oled2:SDA", "esp:8", "green", [ "v-9.6", "h0.07", "v0", "h38.4", "v67.2" ] ],
    [ "btn2:1.l", "esp:4", "green", [ "h0", "v-19.2", "h86.4", "v86.4" ] ],
    [ "btn2:2.l", "esp:GND.2", "green", [ "h-9.6", "v-47.8", "h192" ] ]
  ],
  "dependencies": {}
}